setup.py
c_probability/Binomialdistribution.py
c_probability/Gaussiandistribution.py
c_probability/Generaldistribution.py
c_probability/__init__.py
c_probability.egg-info/PKG-INFO
c_probability.egg-info/SOURCES.txt
c_probability.egg-info/dependency_links.txt
c_probability.egg-info/not-zip-safe
c_probability.egg-info/top_level.txt