Metadata-Version: 1.0
Name: c-probability
Version: 0.1
Summary: Gaussian  and Bionomial distribution
Home-page: UNKNOWN
Author: Cosmos Mahama
Author-email: cosmosmahama@yahoo.com
License: UNKNOWN
Platform: UNKNOWN
